pycli2/__init__.py
pycli2/__main__.py
pycli2/_parser.py
pycli2/app.py
pycli2/py.typed
pycli2-0.1.13.dist-info/licenses/LICENSE.md
pycli2-0.1.13.dist-info/METADATA
pycli2-0.1.13.dist-info/WHEEL
pycli2-0.1.13.dist-info/top_level.txt
pycli2-0.1.13.dist-info/RECORD
