Metadata-Version: 2.4
Name: pycli2
Version: 0.1.13
Summary: Python library to auto parse command line args from function typing.
Author-email: Osvald Lindholm <osvald.lindholm@gmail.com>
License-Expression: GPL-3.0-only
Project-URL: Homepage, https://github.com/Olindholm/pycli2
Project-URL: Source, https://github.com/Olindholm/pycli2.git
Keywords: cli,command,line,arg,interface,parse,typing
Requires-Python: >=3.10
License-File: LICENSE.md
Requires-Dist: pydantic<3,>=2.1; python_version <= "3.12"
Requires-Dist: pydantic<3,>=2.8; python_version == "3.13"
Requires-Dist: pydantic<3,>=2.12; python_version >= "3.14"
Provides-Extra: dev
Requires-Dist: pytest==8.4.2; extra == "dev"
Requires-Dist: pytest-asyncio==1.2.0; extra == "dev"
Requires-Dist: ruff==0.14.4; extra == "dev"
Requires-Dist: pytest-ruff==0.5; extra == "dev"
Requires-Dist: mypy==1.18.2; extra == "dev"
Requires-Dist: pytest-mypy==1.0.1; extra == "dev"
Requires-Dist: types-setuptools==80.9.0.20250822; extra == "dev"
Requires-Dist: setuptools==80.9.0; extra == "dev"
Requires-Dist: semver==3.0.4; extra == "dev"
Requires-Dist: sphinx==8.1.3; extra == "dev"
Requires-Dist: sphinx-rtd-theme==3.0.2; extra == "dev"
Requires-Dist: autoapi==2.0.1; extra == "dev"
Requires-Dist: myst-parser==4.0.1; extra == "dev"
Requires-Dist: ipython==8.37.0; extra == "dev"
Dynamic: license-file
